swarm_mcp/__init__.py
swarm_mcp/server.py
swarm_mcp-0.1.0.dist-info/METADATA
swarm_mcp-0.1.0.dist-info/WHEEL
swarm_mcp-0.1.0.dist-info/entry_points.txt
swarm_mcp-0.1.0.dist-info/licenses/LICENSE
swarm_mcp-0.1.0.dist-info/RECORD
