Metadata-Version: 2.4
Name: swarm-mcp
Version: 0.1.0
Summary: MCP server for Foursquare Swarm check-in data
Project-URL: Homepage, https://github.com/alexpriest/swarm-mcp
Project-URL: Repository, https://github.com/alexpriest/swarm-mcp
Project-URL: Issues, https://github.com/alexpriest/swarm-mcp/issues
Author-email: Alex Priest <hello@alexpriest.com>
License-Expression: MIT
License-File: LICENSE
Keywords: anthropic,checkins,claude,foursquare,mcp,swarm
Classifier: Development Status :: 4 - Beta
Classifier: Intended Audience :: Developers
Classifier: License :: OSI Approved :: MIT License
Classifier: Programming Language :: Python :: 3
Classifier: Programming Language :: Python :: 3.10
Classifier: Programming Language :: Python :: 3.11
Classifier: Programming Language :: Python :: 3.12
Requires-Python: >=3.10
Requires-Dist: httpx>=0.27.0
Requires-Dist: mcp>=1.0.0
